ibraahim/__init__.py
ibraahim/chains/__init__.py
ibraahim/chains/base.py
ibraahim/chains/llm_chain.py
ibraahim/chains/sequential_chain.py
ibraahim/core/__init__.py
ibraahim/core/exceptions.py
ibraahim/core/llm.py
ibraahim/core/types.py
ibraahim/prompts/__init__.py
ibraahim/prompts/template.py
ibraahim/providers/__init__.py
ibraahim/providers/mock.py
ibraahim/providers/openai.py
ibraahim-0.1.0.dist-info/METADATA
ibraahim-0.1.0.dist-info/WHEEL
ibraahim-0.1.0.dist-info/RECORD
