Metadata-Version: 2.4
Name: ibraahim
Version: 0.1.0
Summary: A minimalist, provider-agnostic LLM framework.
Author: Ibraahim Team
Requires-Python: >=3.10,<4.0
Classifier: Programming Language :: Python :: 3
Classifier: Programming Language :: Python :: 3.10
Classifier: Programming Language :: Python :: 3.11
Classifier: Programming Language :: Python :: 3.12
Classifier: Programming Language :: Python :: 3.13
Classifier: Programming Language :: Python :: 3.14
Requires-Dist: openai (>=1.0,<2.0)
Requires-Dist: pydantic (>=2.0,<3.0)
Requires-Dist: python-dotenv (>=1.0,<2.0)
